<?xml version="1.0" encoding="UTF-8"?>

<!DOCTYPE mapper PUBLIC "-//mybatis.org//DTD Mapper 3.0//EN" "http://mybatis.org/dtd/mybatis-3-mapper.dtd">
<!-- 위에는 MyBatis 선언문 -->
<mapper namespace="dev.mvc.cate.CateDAOInter"> <!-- SB가 자동으로 구현하여 연동하는 interface -->
    <insert id="create" parameterType="dev.mvc.cate.CateVO">
       INSERT INTO cate(cateno, grp, name, cnt, seqno, visible, rdate)
       VALUES(CATE_SEQ.nextval, #{grp}, #{name}, 0, #{seqno}, #{visible}, SYSDATE)
    </insert>
    <!-- 레코드 갯수만큼 CateVO class 객체가 생성됨 -> ArrayList<CateVO> 생성됨 -->
    <select id="list_all" resultType="dev.mvc.cate.CateVO">
        SELECT cateno, grp, name, cnt, seqno, visible, rdate
        FROM cate
        ORDER BY seqno ASC
    </select>
    <!-- 하나의 CateVO class 객체가 생성됨 -->
    <select id="read" resultType="dev.mvc.cate.CateVO" parameterType="Integer">
        SELECT cateno, grp, name, cnt, seqno, visible, rdate
        FROM cate
        WHERE cateno = #{cateno}
    </select>
    <!-- return: 수정한 레코드 갯수, parameterType: 수정할 레코드 정보 -->
    <update id="update" parameterType="dev.mvc.cate.CateVO">
        UPDATE cate
        SET grp=#{grp}, name=#{name}, seqno=#{seqno}, visible=#{visible}, rdate=SYSDATE
        WHERE cateno = #{cateno}
    </update>
    <!-- -->
    <delete id="delete" parameterType="int">
        DELETE
        FROM cate
        WHERE cateno = #{cateno}
    </delete>
    <!-- 10등 -> 1등 -->
    <update id="update_seqno_forward" parameterType="int">
        UPDATE cate
        SET seqno = seqno - 1
        WHERE cateno = #{cateno}
    </update>
    <!-- 1등 -> 10등 -->
    <update id="update_seqno_backward" parameterType="int">
        UPDATE cate
        SET seqno = seqno + 1
        WHERE cateno = #{cateno}
    </update>
    <!-- 카테고리 공개 설정 -->
    <update id="update_visible_y" parameterType="int">
        UPDATE cate
        SET visible = 'Y'
        WHERE cateno = #{cateno}
    </update>
    <!-- 카테고리 비공개 설정 -->
    <update id="update_visible_n" parameterType="int">
        UPDATE cate
        SET visible = 'N'
        WHERE cateno = #{cateno}
    </update>
    <!-- 공개된 대분류만 출력 -->
    <select id="list_all_grp_y" resultType="dev.mvc.cate.CateVO">
        SELECT cateno, grp, name, cnt, seqno, visible, rdate
        FROM cate
        WHERE name='--' and visible='Y'
        ORDER BY seqno ASC
    </select>
    <!-- 특정 그룹의 중분류 출력 -->
    <select id="list_all_name_y" resultType="dev.mvc.cate.CateVO" parameterType="String">
        SELECT cateno, grp, name, cnt, seqno, visible, rdate
        FROM cate
        WHERE grp = #{grp} and name != '--' and visible = 'Y'
        ORDER BY seqno ASC
    </select>

</mapper>